agents_boot/__init__.py
agents_boot/__main__.py
agents_boot/config.py
agents_boot/gtm_cli.py
agents_boot/utils.py
agents_boot/agents/__init__.py
agents_boot/agents/graph.py
agents_boot/agents/gtm_graph.py
agents_boot/agents/post_release_graph.py
agents_boot/agents/autonomy/product_growth_graph.py
agents_boot/channels/aws_marketplace.py
agents_boot/channels/base.py
agents_boot/channels/dockerhub.py
agents_boot/channels/pypi.py
agents_boot/channels/website.py
agents_boot/evals/__init__.py
agents_boot/evals/gate.py
agents_boot/evals/run_eval.py
agents_boot/observability/__init__.py
agents_boot/observability/otel.py
agents_boot/server/__init__.py
agents_boot/server/__main__.py
agents_boot/server/api.py
agents_boot/server/deps/auth.py
agents_boot/server/routes/__init__.py
agents_boot/server/routes/auto_routes.py
agents_boot/server/routes/console_gtm.py
agents_boot/server/routes/dwell.py
agents_boot/server/routes/dwell_db.py
agents_boot/server/routes/eta.py
agents_boot/server/routes/eta_db.py
agents_boot/server/routes/gtm.py
agents_boot/server/routes/ingest_db.py
agents_boot/server/routes/run.py
agents_boot/server/routes/shipments.py
agents_boot/static/__init__.py
agents_boot/tools/__init__.py
agents_boot/tools/repo_search.py
agents_boot/tools/spec_linter.py
agents_boot/tools/spec_to_tests.py
agents_boot/utils/release_log.py
autogen_scv/__init__.py
novachain/__init__.py
novachain/billing/stripe_meter.py
novachain/data/__init__.py
novachain/data/ingest/__init__.py
novachain/data/ingest/csv_ingestor.py
novachain/db/models.py
novachain/db/session.py
novachain/domain/__init__.py
novachain/domain/schemas.py
novachain/dq/__init__.py
novachain/dq/checks.py
novachain/dq/run_checks.py
novachain/services/__init__.py
novachain/services/dwell/__init__.py
novachain/services/dwell/service.py
novachain/services/eta/__init__.py
novachain/services/eta/service.py
novachain-0.1.0.dist-info/METADATA
novachain-0.1.0.dist-info/WHEEL
novachain-0.1.0.dist-info/entry_points.txt
novachain-0.1.0.dist-info/top_level.txt
novachain-0.1.0.dist-info/RECORD
